awstool/__init__.py
awstool/account.py
awstool/cli.py
awstool/config.py
awstool/configure.py
awstool/credential.py
awstool-0.0.4.dist-info/LICENSE
awstool-0.0.4.dist-info/METADATA
awstool-0.0.4.dist-info/WHEEL
awstool-0.0.4.dist-info/entry_points.txt
awstool-0.0.4.dist-info/top_level.txt
awstool-0.0.4.dist-info/RECORD
