Metadata-Version: 2.1
Name: awstool
Version: 0.0.4
Summary: Command Line Environment for federation or AMS AWS users
Home-page: https://github.com/zhan9san/aws-tool
Author: zhan9san
Author-email: zhan9san@163.com
License: GPLv3
Platform: UNKNOWN
Classifier: Programming Language :: Python :: 3
Classifier: License :: OSI Approved :: MIT License
Classifier: Operating System :: OS Independent
Requires-Python: >=3.6
Requires-Dist: boto3
Requires-Dist: requests
Requires-Dist: beautifulsoup4
Requires-Dist: pyyaml
